[{"model": "store.artist", "pk": 2, "fields": {"name": "Francis Cabrel"}}, {"model": "store.artist", "pk": 3, "fields": {"name": "Celine Dion"}}, {"model": "store.artist", "pk": 4, "fields": {"name": "Matt Pokora"}}, {"model": "store.artist", "pk": 5, "fields": {"name": "Maitre Gims"}}, {"model": "store.contact", "pk": 10, "fields": {"email": "thomas@gmail.com", "name": "Thomas"}}, {"model": "store.album", "pk": 3, "fields": {"reference": 2, "create_at": "2023-02-12T18:18:52.217Z", "available": false, "title": "S'il suffisait d'aimer", "picture": "https://static.fnac-static.com/multimedia/FR/Images_Produits/FR/fnac.com/Visual_Principal_340/0/2/9/5099749185920/tsp20120926093943/S-il-suffisait-d-aimer.jpg", "artists": [3]}}, {"model": "store.album", "pk": 4, "fields": {"reference": 2, "create_at": "2023-02-12T19:48:39.326Z", "available": false, "title": "My Way", "picture": "https://static.fnac-static.com/multimedia/Images/FR/NR/33/84/7f/8356915/1540-1/tsp20160909080022/My-Way.jpg", "artists": [4]}}, {"model": "store.album", "pk": 5, "fields": {"reference": 7, "create_at": "2023-02-12T19:50:17.227Z", "available": false, "title": "Le Fléau", "picture": "https://static.fnac-static.com/multimedia/Images/FR/NR/13/40/c2/12730387/1540-1/tsp20201008141115/Le-Fleau.jpg", "artists": [5]}}, {"model": "store.booking", "pk": 13, "fields": {"created_at": "2023-04-21T10:02:36.516Z", "contacted": false, "contact": 10, "album": 5}}, {"model": "store.booking", "pk": 14, "fields": {"created_at": "2023-04-21T10:02:58.520Z", "contacted": false, "contact": 10, "album": 3}}, {"model": "store.booking", "pk": 15, "fields": {"created_at": "2023-04-21T10:03:19.492Z", "contacted": false, "contact": 10, "album": 4}}]